{
  "id": "scourge",
  "label": "Scourge",
  "description": "Prince's errand. The problem doesn't wake up.",
  "modifiers": {
    "weights": {
      "in_clan_disciplines": 0.1
    },
    "skill_biases": {
      "firearms": 0.4,
      "intimidation": 0.4,
      "stealth": 0.15,
      "brawl": 0.3
    },
    "discipline_biases": {
      "potence": 0.25,
      "celerity": 0.15,
      "presence": 0.3
    },
    "flaw_biases": {
      "obvious_predator": 0.3,
      "bestial_temper": 0.25
    },
    "discipline_power_biases": {
      "dread_gaze": 0.4,
      "daunt": 0.5,
      "prowess": 0.0,
      "lethal_body": 0.05
    },
    "tag_affinities": {
      "intimidation": 0.4,
      "combat": 0.35
    }
  }
}
